/*
 * Instrucoes.h
 *
 *  Created on: 08/02/2013
 *      Author: Vitor
 */

#ifndef INSTRUCOES_H_
#define INSTRUCOES_H_

#include <stdio.h>
#include <stdlib.h>
#include <string.h>
#include "Frame.h"
#include "Execucao.h"
#include "ClassLoader.h"
#include "FuncoesGerais.h"
#include "ClassFile.h"

int nop(execucao *p); // 0x00
int aconst_null(execucao *p); // 0x01
int iconst_m1(execucao *p); //0x2
int iconst_0(execucao *p);// 0x3
int iconst_1(execucao *p);// 0x4
int iconst_2(execucao *p);// 0x5
int iconst_3(execucao *p);// 0x6
int iconst_4(execucao *p);// 0x7
int iconst_5(execucao *p);// 0x8
int lconst_0(execucao *p);// 0x9
int lconst_1(execucao *p);// 0xA
int fconst_0(execucao *p);// 0xB
int fconst_1(execucao *p);// 0xC
int fconst_2(execucao *p);// 0xD
int dconst_0(execucao *p);// 0xE
int dconst_1(execucao *p);// 0xF

// push ------------------------------------------------------------
int bipush(execucao *p);// 0x10
int sipush(execucao *p);// 0x11

int ldc(execucao *p); // 0x12
int ldc_w(execucao *p); // 0x13
int ldc2_w(execucao *p); // 0x14

// load ------------------------------------------------------------
int iload(execucao *p);//0x15
int lload(execucao *p);//0x16
int fload(execucao *p);//0x17
int dload(execucao *p);//0x18
int aload(execucao *p);//0x19
int iload_0(execucao *p); //0x1A
int iload_1(execucao *p); // 0X1B
int iload_2(execucao *p); // 0X1C
int iload_3(execucao *p); // 0X1D
int lload_0(execucao *p); // 0x1E
int lload_1(execucao *p); // 0x1F
int lload_2(execucao *p); // 0x20
int lload_3(execucao *p); // 0x21
int fload_0(execucao *p); // 0x22
int fload_1(execucao *p); // 0x23
int fload_2(execucao *p); // 0x24
int fload_3(execucao *p); // 0x25
int dload_0(execucao *p); // 0x26
int dload_1(execucao *p); // 0x27
int dload_2(execucao *p); // 0x28
int dload_3(execucao *p); // 0x29
int aload_0(execucao *p); // 0x2A
int aload_1(execucao *p); // 0x2B
int aload_2(execucao *p); // 0x2C
int aload_3(execucao *p); // 0x2D

//Aload ---------------------------------------------------------------
int iaload(execucao *p); // 0x2E , 0X33 , 0X34 , 0X35
int laload(execucao *p); // 0X2F
int faload(execucao *p);// 0X 30
int daload(execucao *p); // 0X31
int aaload(execucao *p); // 0X32

// store ------------------------------------------------------------

int store(execucao *p); // 0x36 , 0x37 , 0x38, 0x39 , 0x3A
int store_0(execucao *p); //0x3B , 0X3F , 0X43 , 0X47 , 0X4B
int store_1(execucao *p); //0X3C , 0X40 , 0X44 , 0X48 , 0X4C
int store_2(execucao *p); //0X3D , 0X41 , 0X45 , 0X49 , 0X4D
int store_3(execucao *p); //0X3E , 0X42 , 0X46 , 0X4A , 0X4E

//Astore -----------------------------------------------------------

int iastore(execucao *p); //0x4f , 0x54 , 0x55 , 0x56
int lastore(execucao *p); //0x50
int fastore(execucao *p);//0x51
int dastore(execucao *p);//0x52
int aastore(execucao *p);//0x53


// dup --------------------------------------------------------------
int dup(execucao *p);// 0x59
int dup_x1(execucao *p); // 0x5A
int dup_x2(execucao *p); // 0x5B
int dup2(execucao *p); // 0x5C
int dup2_x1(execucao *p); // 0x5D
int dup2_x2(execucao *p); // 0x5E
// swap ----------------------------------------------------------
int swap(execucao *p);  //0x5F
// add ------------------------------------------------------------

int iadd(execucao *p);  //0x60
int ladd(execucao *p);  //0x61
int fadd(execucao *p);  //0x62
int dadd(execucao *p);  //0x63
// sub ------------------------------------------------------------

int isub(execucao *p);  //0x64
int lsub(execucao *p);  //0x65
int fsub(execucao *p);  //0x66
int dsub(execucao *p);  //0x67

// mul ------------------------------------------------------------
int imul(execucao *p);  //0x68
int lmul(execucao *p);  //0x69
int fmul(execucao *p);  //0x6A
int dmul(execucao *p);  //0x6B

// div-------------------------------------------------------------
int idiv(execucao *p);  //0x6C
int ldiv_(execucao *p);  //0x6D
int fdiv(execucao *p);  //0x6E
int ddiv(execucao *p);  //0x6F

// rem -----------------------------------------------------------
int irem(execucao *p);  //0x70
int lrem(execucao *p);  //0x71
int frem(execucao *p);  //0x72
int drem_(execucao *p);  //0x73

// neg -----------------------------------------------------------
int ineg(execucao *p);  //0x74
int lneg(execucao *p);  //0x75
int fneg(execucao *p);  //0x76
int dneg(execucao *p);  //0x77

// shl -----------------------------------------------------------
int ishl(execucao *p);  //0x78
int lshl(execucao *p);  //0x79

// shr -----------------------------------------------------------
int ishr(execucao *p);  //0x7A
int lshr(execucao *p);  //0x7B
//ushift -----------------------------------------------------------
int iushr(execucao *p); //0x7C
int lushr(execucao *p);//0x7D

//Bitwise ---------------------------------------------------------
int iand(execucao *p);  //0x7E
int land(execucao *p);  //0x7F
int ior(execucao *p);  //0x80
int lor(execucao *p);  //0x81
int ixor(execucao *p);  //0x82
int lxor(execucao *p);  //0x83
int iinc(execucao *p); // 0x84


//x2y -------------------------------------------------------------
int i2l(execucao *p);  //0x85
int i2f(execucao *p);  //0x86
int i2d(execucao *p);  //0x87

int l2i(execucao *p);  //0x88
int l2f(execucao *p);  //0x89
int l2d(execucao *p);  //0x8A

int f2i(execucao *p);  //0x8B
int f2l(execucao *p);  //0x8C
int f2d(execucao *p);  //0x8D

int d2i(execucao *p);  //0x8E
int d2l(execucao *p);  //0x8F
int d2f(execucao *p);  //0x90

int i2c(execucao *p);  //0x91, 0x92
int i2s(execucao *p);  //0x93
//XcmpY ------------------------------------------------------------------
int lcmp(execucao *p);//0x94
int fcmpl(execucao *p);//0x95
int fcmpg(execucao *p);//0x96
int dcmpl(execucao *p);//0x97
int dcmpg(execucao *p);//0x98
// IF --------------------------------------------------------------------
int ifeq(execucao *p);//0x99
int ifne(execucao *p);//0x9A
int iflt(execucao *p);//0x9B
int ifge(execucao *p);//0x9C
int ifgt(execucao *p);//0x9D
int ifle(execucao *p);//0x9E
int if_icmpeq(execucao *p);//0x9F
int if_icmpne(execucao *p);//0xA0
int if_icmplt(execucao *p);//0xA1
int if_icmpge(execucao *p);//0xA2
int if_icmpgt(execucao *p);//0xA3
int if_icmple(execucao *p);//0xA4
int if_acmpeq(execucao *p);//0xA5
int if_acmpne(execucao *p);//0xA6

// controle ---------------------------------------------------------
int goto_(execucao *p); // 0xA7
int jsr(execucao *p); // 0xA8
int ret(execucao *p); // 0xA9
//Switch -------------------------------------------------------------

int tableswitch(execucao *p);//0xAA
int lookupswitch(execucao *p);//0xAB
// retornos ------------------------------------------------------
int ireturn(execucao *p);  //0xAC
int lreturn(execucao *p);  //0xAD
int freturn(execucao *p);  //0xAE
int dreturn(execucao *p);  //0xAF
int areturn(execucao *p);  //0xB0
int return_(execucao *p);  //0xB1

// static --------------------------------------------------------
int getstatic(execucao *p); // 0xB2
int putstatic(execucao *p); // 0xB3

// invokes -------------------------------------------------------
int invokevirtual(execucao *p); // 0xB6
int invokespecial(execucao *p); // 0xB7
int invokestatic(execucao *p); // 0xB8

//Array ------------------------------------------------------------
int newarray(execucao *p); //0xBC
int anewarray(execucao *p); //0xBD
int arraylength(execucao *p); // 0xBE
int multianewarray(execucao *p);// 0xC5
//if_null------------------------------------------------------------
int ifnull(execucao *p);//0xC6
int ifnonnull(execucao *p);//0xc7
//controle_wide----------------------------------------------------------
int goto_w(execucao *p); //0xC8
int jsr_w(execucao *p); //0xC9

int (*vetInstr[])(execucao *p) ;

#endif /* INSTRUCOES_H_ */
